{
  "scenario": "baseline",
  "seed": 12648430,
  "duration_ns": 5461747014,
  "success_count": 2800,
  "drop_count": 0,
  "verify_fail_count": 0,
  "attacks_injected": 0,
  "attacks_detected": 0,
  "attacks_delivered": 0,
  "tx_bytes_total": 484800,
  "rx_bytes_total": 484800,
  "deadline_miss": {
    "D1": {"miss": 1, "total": 600},
    "D2": {"miss": 0, "total": 600},
    "D3": {"miss": 0, "total": 600},
    "D4": {"miss": 0, "total": 400},
    "D5": {"miss": 0, "total": 400},
    "D6": {"miss": 0, "total": 200}
  },
  "histograms": {
    "e2e_latency": {
      "count": 2800, "min_ns": 624378, "max_ns": 5891582,
      "mean_ns": 1948972.72, "stddev_ns": 555106.18,
      "p50_ns": 2294256, "p95_ns": 2404074, "p99_ns": 2509532, "p999_ns": 3435497
    },
    "secoc_auth": {
      "count": 2800, "min_ns": 2443, "max_ns": 3391242,
      "mean_ns": 6800.44, "stddev_ns": 64043.98,
      "p50_ns": 4734, "p95_ns": 10191, "p99_ns": 15509, "p999_ns": 32906
    },
    "secoc_verify": {
      "count": 2800, "min_ns": 4298, "max_ns": 73020,
      "mean_ns": 12743.97, "stddev_ns": 4314.98,
      "p50_ns": 12061, "p95_ns": 18755, "p99_ns": 30390, "p999_ns": 43707
    },
    "cantp": {
      "count": 2800, "min_ns": 936, "max_ns": 233107,
      "mean_ns": 13098.66, "stddev_ns": 14311.23,
      "p50_ns": 10039, "p95_ns": 24355, "p99_ns": 38612, "p999_ns": 223859
    },
    "bus_transit": {
      "count": 0, "min_ns": 0, "max_ns": 0,
      "mean_ns": 0.00, "stddev_ns": 0.00,
      "p50_ns": 0, "p95_ns": 0, "p99_ns": 0, "p999_ns": 0
    },
    "pdu_bytes": {
      "count": 2800, "min_ns": 30, "max_ns": 1050,
      "mean_ns": 173.14, "stddev_ns": 279.36,
      "p50_ns": 42, "p95_ns": 1050, "p99_ns": 1050, "p999_ns": 1050
    },
    "fragments": {
      "count": 2800, "min_ns": 1, "max_ns": 5,
      "mean_ns": 1.79, "stddev_ns": 1.52,
      "p50_ns": 1, "p95_ns": 5, "p99_ns": 5, "p999_ns": 5
    }
  }
}
